vinsgrad/__init__.py
vinsgrad/core/__init__.py
vinsgrad/core/engine.py
vinsgrad/functional/__init__.py
vinsgrad/functional/softmax.py
vinsgrad/nn/__init__.py
vinsgrad/nn/_activations.py
vinsgrad/nn/activation_modules.py
vinsgrad/nn/conv2d.py
vinsgrad/nn/linear.py
vinsgrad/nn/losses.py
vinsgrad/nn/maxpool2d.py
vinsgrad/nn/module.py
vinsgrad/optim/SGD.py
vinsgrad/optim/__init__.py
vinsgrad/optim/_optimizer.py
vinsgrad/utils/__init__.py
vinsgrad/utils/im2col_utils.py
vinsgrad/utils/save_load.py
vinsgrad/utils/utils.py
vinsgrad/utils/data/__init__.py
vinsgrad/utils/data/data_loader.py
vinsgrad/utils/data/random_split.py
vinsgrad/utils/data/subset_dataset.py
vinsgrad/vision/__init__.py
vinsgrad/vision/transforms.py
vinsgrad/vision/vision_dataset.py
vinsgrad/vision/datasets/__init__.py
vinsgrad/vision/datasets/mnist.py
vinsgrad-0.1.3.dist-info/LICENSE
vinsgrad-0.1.3.dist-info/METADATA
vinsgrad-0.1.3.dist-info/WHEEL
vinsgrad-0.1.3.dist-info/top_level.txt
vinsgrad-0.1.3.dist-info/RECORD
